confedit/__init__.py
confedit/conf.py
confedit-0.1.1.dist-info/entry_points.txt
confedit-0.1.1.dist-info/WHEEL
confedit-0.1.1.dist-info/METADATA
confedit-0.1.1.dist-info/RECORD
