Metadata-Version: 2.1
Name: confedit
Version: 0.1.1
Summary: 
Home-page: UNKNOWN
License: UNKNOWN
Author: Dominic Looser
Author-email: dominic.looser@gmail.com
Requires-Python: >=3.7,<4.0
Classifier: Programming Language :: Python :: 3
Classifier: Programming Language :: Python :: 3.7
Requires-Dist: click (>=7.0,<8.0)
Requires-Dist: pick (>=0.6.4,<0.7.0)
